{
  "name": "NestJS Dev Container",
  "dockerComposeFile": "docker-compose.yml",
  "service": "app",
  "workspaceFolder": "/app",
  "shutdownAction": "stopCompose",
  "extensions": [
    "esbenp.prettier-vscode",
    "dbaeumer.vscode-eslint",
    "Prisma.prisma"
  ],
  "settings": {
    // Habilita formatar ao salvar
    "editor.formatOnSave": true,

    // Prettier como formatador padrão para linguagens específicas
    "[typescript]": {
      "editor.defaultFormatter": "esbenp.prettier-vscode"
    },
    "[javascript]": {
      "editor.defaultFormatter": "esbenp.prettier-vscode"
    },
    "[json]": {
      "editor.defaultFormatter": "esbenp.prettier-vscode"
    },

    // Habilita ESLint
    "eslint.enable": true,
    "eslint.format.enable": true,
    "editor.codeActionsOnSave": {
      "source.fixAll.eslint": true
    }
  },
  "remoteUser": "node"
}
